superclient/__init__.py
superclient/logger.py
superclient/agent/__init__.py
superclient/agent/clients.py
superclient/agent/interceptor.py
superclient/agent/metadata.py
superclient/agent/patches.py
superclient/agent/tracker.py
superclient/core/manager.py
superclient/core/reporter.py
superclient/model/messages.py
superclient/util/config.py
superclient/util/network.py
superclient_beta-1.0.0.dist-info/licenses/LICENSE
superclient_beta-1.0.0.dist-info/METADATA
superclient_beta-1.0.0.dist-info/WHEEL
superclient_beta-1.0.0.dist-info/top_level.txt
superclient_beta-1.0.0.dist-info/RECORD
