Metadata-Version: 2.4
Name: superclient-beta
Version: 1.0.0
Summary: Superstream optimisation library for Kafka producers
Author-email: Superstream Labs <support@superstream.ai>
License: Apache-2.0
Project-URL: Homepage, https://github.com/superstreamlabs/superclient-python
Classifier: License :: OSI Approved :: Apache Software License
Classifier: Programming Language :: Python :: 3
Classifier: Programming Language :: Python :: 3 :: Only
Classifier: Operating System :: OS Independent
Classifier: Topic :: System :: Networking
Requires-Python: >=3.8
License-File: LICENSE
Dynamic: license-file
